dormai/__init__.py
dormai/api.py
dormai/async_api.py
dormai-0.1.3.dist-info/METADATA
dormai-0.1.3.dist-info/WHEEL
dormai-0.1.3.dist-info/RECORD
