Metadata-Version: 2.3
Name: dormai
Version: 0.1.3
Summary: 
Author: George Kasparyants
Author-email: gg_plastt@mail.ru
Requires-Python: >=3.10
Classifier: Programming Language :: Python :: 3
Classifier: Programming Language :: Python :: 3.10
Classifier: Programming Language :: Python :: 3.11
Classifier: Programming Language :: Python :: 3.12
Classifier: Programming Language :: Python :: 3.13
Requires-Dist: httpx (>=0.28.1,<0.29.0)
Requires-Dist: pydantic (>=2.10.6,<3.0.0)
Requires-Dist: pyyaml (>=6.0.2,<7.0.0)
